django_lti_provider-1.1.0.dist-info/licenses/AUTHORS.md
django_lti_provider-1.1.0.dist-info/licenses/LICENSE
lti_provider/__init__.py
lti_provider/admin.py
lti_provider/auth.py
lti_provider/lti.py
lti_provider/mixins.py
lti_provider/models.py
lti_provider/urls.py
lti_provider/views.py
lti_provider/migrations/0001_initial.py
lti_provider/migrations/0002_auto_20151231_1107.py
lti_provider/migrations/0003_auto_20151231_1109.py
lti_provider/migrations/0004_lticoursecontext_enable.py
lti_provider/migrations/0005_auto_20171009_1234.py
lti_provider/migrations/0006_auto_20180205_1636.py
lti_provider/migrations/0007_alter_lticoursecontext_lms_course_context.py
lti_provider/migrations/__init__.py
lti_provider/templates/lti_provider/config.xml
lti_provider/templates/lti_provider/fail_auth.html
lti_provider/templates/lti_provider/fail_course_configuration.html
lti_provider/templates/lti_provider/landing_page.html
lti_provider/templatetags/__init__.py
lti_provider/templatetags/lti_utils.py
lti_provider/tests/__init__.py
lti_provider/tests/factories.py
lti_provider/tests/test_auth.py
lti_provider/tests/test_lti.py
lti_provider/tests/test_templatetags.py
lti_provider/tests/test_views.py
lti_provider/tests/urls.py
django_lti_provider-1.1.0.dist-info/METADATA
django_lti_provider-1.1.0.dist-info/WHEEL
django_lti_provider-1.1.0.dist-info/top_level.txt
django_lti_provider-1.1.0.dist-info/RECORD
