Metadata-Version: 2.4
Name: django-lti-provider
Version: 1.1.0
Summary: LTI helper
Home-page: https://github.com/ccnmtl/django-lti-provider
Author: Susan Dreher
Author-email: ctl-dev@columbia.edu
License: BSD
Platform: any
License-File: LICENSE
License-File: AUTHORS.md
Requires-Dist: Django
Requires-Dist: nameparser
Requires-Dist: httplib2
Requires-Dist: oauth2
Requires-Dist: oauthlib
Requires-Dist: pylti
Requires-Dist: pylti1p3
Dynamic: author
Dynamic: author-email
Dynamic: description
Dynamic: home-page
Dynamic: license
Dynamic: license-file
Dynamic: platform
Dynamic: requires-dist
Dynamic: summary
